linear_mcp/__init__.py
linear_mcp/_version.py
linear_mcp/linear.py
linear_mcp/linear_service.py
linear_mcp/server_logger.py
linear_mcp-0.1.7.data/data/requirements.txt
linear_mcp-0.1.7.dist-info/METADATA
linear_mcp-0.1.7.dist-info/WHEEL
linear_mcp-0.1.7.dist-info/entry_points.txt
linear_mcp-0.1.7.dist-info/top_level.txt
linear_mcp-0.1.7.dist-info/RECORD
