Metadata-Version: 2.4
Name: linear-mcp
Version: 0.1.7
Summary: Another Linear MCP Server
Home-page: https://github.com/context-labs/linear-mcp
Author-email: Kyle Pena <kyle.pena@kuzco.xyz>
License: MIT
Project-URL: Homepage, https://github.com/context-labs/linear-mcp
Project-URL: Repository, https://github.com/context-labs/linear-mcp.git
Requires-Python: >=3.12
Requires-Dist: httpx>=0.28.1
Requires-Dist: python-dotenv>=1.0.1
Requires-Dist: pydantic>=2.10.6
Requires-Dist: mcp>=0.4.0
Dynamic: home-page
Dynamic: requires-python
